spiepy/__init__.py
spiepy/flatten.py
spiepy/init.py
spiepy/locate.py
spiepy/mask.py
spiepy/measure.py
spiepy/demo/__init__.py
spiepy/demo/demos.py
spiepy/demo/image_with_defects.dat
spiepy/demo/image_with_step_edge.dat
spiepy/demo/image_with_step_edge_and_atoms.dat
SPIEPy-0.2.1.dist-info/LICENSE
SPIEPy-0.2.1.dist-info/METADATA
SPIEPy-0.2.1.dist-info/WHEEL
SPIEPy-0.2.1.dist-info/top_level.txt
SPIEPy-0.2.1.dist-info/RECORD
