Metadata-Version: 2.1
Name: SPIEPy
Version: 0.2.1
Summary: SPIEPy (Scanning Probe Image Enchanter using Python) is a Python library to improve automatic processing of SPM images.
Author: Stephan Zevenhuizen
Author-email: S.J.M.Zevenhuizen@uu.nl
License: BSD-2-Clause
Project-URL: documentation, https://webspace.science.uu.nl/~zeven101/SPIEPy/
Keywords: SPM,scanning,probe,microscopy,image,analysis,flattening,nano,nanotechnology
Classifier: Topic :: Scientific/Engineering :: Chemistry
Classifier: Topic :: Scientific/Engineering :: Information Analysis
Classifier: Topic :: Scientific/Engineering :: Physics
Classifier: Topic :: Software Development :: Libraries :: Python Modules
Classifier: Development Status :: 5 - Production/Stable
Classifier: License :: OSI Approved :: BSD License
Classifier: Programming Language :: Python :: 3
Classifier: Operating System :: OS Independent
Classifier: Intended Audience :: Science/Research
Classifier: Natural Language :: English
Requires-Python: >=3.8
License-File: LICENSE
Requires-Dist: numpy
Requires-Dist: scipy
Requires-Dist: matplotlib
